mlplot/__init__.py
mlplot/classification.py
mlplot/errors.py
mlplot/utilities.py
mlplot/evaluation/__init__.py
mlplot/evaluation/classification.py
mlplot/evaluation/comparison.py
mlplot/evaluation/decorators.py
mlplot/evaluation/evaluation.py
mlplot/evaluation/regression.py
mlplot/model_evaluation/__init__.py
mlplot/model_evaluation/classifier.py
mlplot/model_evaluation/model_evaluation.py
mlplot/test/__init__.py
mlplot/test/test_classification.py
mlplot-0.0.3.dist-info/METADATA
mlplot-0.0.3.dist-info/RECORD
mlplot-0.0.3.dist-info/WHEEL
mlplot-0.0.3.dist-info/top_level.txt
tests/__init__.py
tests/test_classification.py
tests/test_utilities.py
tests/evaluation/__init__.py
tests/evaluation/test_classification.py
tests/evaluation/test_comparison.py
tests/evaluation/test_evaluation.py
tests/evaluation/test_regression.py
tests/model_evaluation/__init__.py
tests/model_evaluation/test_classifier.py
tests/model_evaluation/test_model_evaluation.py
