Metadata-Version: 2.1
Name: mlplot
Version: 0.0.3
Summary: UNKNOWN
Home-page: https://github.com/sbarton272/mlplot
Author: sbarton272
License: MIT License
Platform: UNKNOWN
Classifier: Development Status :: 3 - Alpha
Classifier: Intended Audience :: Developers
Classifier: Topic :: Scientific/Engineering :: Visualization
Classifier: License :: OSI Approved :: MIT License
Classifier: Programming Language :: Python :: 3
Classifier: Programming Language :: Python :: 3.5
Classifier: Programming Language :: Python :: 3.6
Requires-Dist: matplotlib (>=2.2.3)
Requires-Dist: numpy (>=1.15.1)
Requires-Dist: scipy (>=1.1.0)
Requires-Dist: scikit-learn (>=0.19.2)
